ntupro/__init__.py
ntupro/booking.py
ntupro/inspect.py
ntupro/optimization.py
ntupro/run.py
ntupro/variations.py
ntupro/utils/__init__.py
ntupro/utils/_booking.py
ntupro/utils/_optimization.py
ntupro/utils/_printing.py
ntupro/utils/_run.py
ntupro/utils/_variations.py
tests/__init__.py
tests/test_booking.py
ntupro-0.0.0.dist-info/LICENSE
ntupro-0.0.0.dist-info/METADATA
ntupro-0.0.0.dist-info/WHEEL
ntupro-0.0.0.dist-info/top_level.txt
ntupro-0.0.0.dist-info/RECORD
