Metadata-Version: 2.1
Name: ntupro
Version: 0.0.0
Summary: Innovative package to optimize HEP analyses based on ROOT RDataFrame
Home-page: https://github.com/maxgalli/ntupro
Author: Massimiliano Galli
Author-email: massimiliano.galli.95@gmail.com
License: UNKNOWN
Platform: UNKNOWN
Classifier: Programming Language :: Python :: 3
Classifier: License :: OSI Approved :: MIT License
Classifier: Operating System :: OS Independent
Requires-Python: >=3.6
